setup.py
ucontextlib.py
micropython_ucontextlib.egg-info/PKG-INFO
micropython_ucontextlib.egg-info/SOURCES.txt
micropython_ucontextlib.egg-info/dependency_links.txt
micropython_ucontextlib.egg-info/top_level.txt